Metadata-Version: 1.1
Name: caketestoopschool
Version: 0.0.2
Summary: OOP School by CKDEV
Home-page: https://github.com/petjarin/caketestoopschool
Author: CKDEV
Author-email: cakesesaweah@gmail.com
License: MIT
Download-URL: https://github.com/petjarin/caketestoopschool/archive/v0.0.2.zip
Keywords: OOP,School,CKDEV
Platform: UNKNOWN
Classifier: Development Status :: 3 - Alpha
Classifier: Intended Audience :: Education
Classifier: Topic :: Software Development :: Build Tools
Classifier: License :: OSI Approved :: MIT License
Classifier: Programming Language :: Python :: 3
Classifier: Programming Language :: Python :: 3.4
Classifier: Programming Language :: Python :: 3.5
Classifier: Programming Language :: Python :: 3.6
Classifier: Programming Language :: Python :: 3.7
Classifier: Programming Language :: Python :: 3.8
Classifier: Programming Language :: Python :: 3.9
